cardiolife_apiclient/APIclient.py
cardiolife_apiclient/__init__.py
cardiolife_apiclient-1.0.1.dist-info/METADATA
cardiolife_apiclient-1.0.1.dist-info/WHEEL
cardiolife_apiclient-1.0.1.dist-info/top_level.txt
cardiolife_apiclient-1.0.1.dist-info/RECORD
