Metadata-Version: 2.4
Name: cardiolife-apiclient
Version: 1.0.1
Summary: Python client for the Cardiolife ECG API Server
Home-page: https://cardiolife.global
Author: Andre Costa
Author-email: ac@cardiolife.global
Classifier: Programming Language :: Python :: 3
Classifier: License :: OSI Approved :: MIT License
Classifier: Operating System :: OS Independent
Requires-Python: >=3.7
Requires-Dist: requests>=2.25.0
Requires-Dist: numpy>=1.21.0
Dynamic: author
Dynamic: author-email
Dynamic: classifier
Dynamic: description
Dynamic: description-content-type
Dynamic: home-page
Dynamic: requires-dist
Dynamic: requires-python
Dynamic: summary
